mailpilot/__init__.py
mailpilot/config.py
mailpilot/mailpilot.py
mailpilot/utils.py
MailPilot-1.0.0.dist-info/LICENSE
MailPilot-1.0.0.dist-info/METADATA
MailPilot-1.0.0.dist-info/WHEEL
MailPilot-1.0.0.dist-info/entry_points.txt
MailPilot-1.0.0.dist-info/top_level.txt
MailPilot-1.0.0.dist-info/RECORD
