Metadata-Version: 2.1
Name: MailPilot
Version: 1.0.0
Summary: A versatile email sending tool for personalized mass mailing.
Home-page: https://github.com/plawlost/MailPilot
Author: Yağız Erkam '@plawlost' Çelebi
Author-email: contact@plawlost.com
License: Apache License 2.0
Platform: UNKNOWN
Classifier: Development Status :: 4 - Beta
Classifier: Intended Audience :: Developers
Classifier: Topic :: Software Development :: Build Tools
Classifier: License :: OSI Approved :: Apache Software License
Classifier: Programming Language :: Python :: 3
Classifier: Intended Audience :: Information Technology
Classifier: Natural Language :: English
Classifier: Programming Language :: Python :: 3.6
Classifier: Programming Language :: Python :: 3.7
Classifier: Programming Language :: Python :: 3.8
Classifier: Programming Language :: Python :: 3.9
Classifier: Programming Language :: Python :: 3.10
Classifier: Operating System :: OS Independent
Requires-Python: >=3.6.0
License-File: LICENSE
